sanix/__init__.py
sanix/const.py
sanix/exceptions.py
sanix/models.py
sanix-1.0.5.dist-info/LICENCE
sanix-1.0.5.dist-info/METADATA
sanix-1.0.5.dist-info/WHEEL
sanix-1.0.5.dist-info/top_level.txt
sanix-1.0.5.dist-info/RECORD
