Metadata-Version: 2.1
Name: sanix
Version: 1.0.5
Summary: Python wrapper for getting measurements data from Sanix devices.
Home-page: https://github.com/tomaszsluszniak/sanix_py
Author: Tomasz Słuszniak
Author-email: tomasz.sluszniak@gmail.com
License: MIT
Classifier: Programming Language :: Python :: 3
Classifier: License :: OSI Approved :: MIT License
Classifier: Operating System :: OS Independent
Requires-Python: >=3.10.0
License-File: LICENCE
Requires-Dist: requests
